carte_cli/__init__.py
carte_cli/extractor/__init__.py
carte_cli/extractor/glue_extractor.py
carte_cli/extractor/json_schema_extractor.py
carte_cli/loader/__init__.py
carte_cli/loader/carte_loader.py
carte_cli/main.py
carte_cli/model/__init__.py
carte_cli/model/carte_table_model.py
carte_cli/model/job_metadata.py
carte_cli/publisher/remove_deleted_publisher.py
carte_cli/scaffolding/__init__.py
carte_cli/scaffolding/frontend.py
carte_cli/utils/__init__.py
carte_cli/utils/config_parser.py
carte_cli/utils/file_io.py
carte_cli/utils/flatten.py
carte_cli/utils/frontmatter.py
carte_cli/utils/templates/dataset_flattened.md
carte_cli-0.3.27.dist-info/entry_points.txt
carte_cli-0.3.27.dist-info/COPYING
carte_cli-0.3.27.dist-info/WHEEL
carte_cli-0.3.27.dist-info/METADATA
carte_cli-0.3.27.dist-info/RECORD
