Metadata-Version: 2.1
Name: carte-cli
Version: 0.3.27
Summary: A static site generator for data catalogs
Home-page: https://cartedata.com
License: GPL-3.0-or-later
Author: Balint Haller
Author-email: balint@hey.com
Requires-Python: >=3.8,<4.0
Classifier: License :: OSI Approved :: GNU General Public License v3 or later (GPLv3+)
Classifier: Programming Language :: Python :: 3
Classifier: Programming Language :: Python :: 3.10
Classifier: Programming Language :: Python :: 3.8
Classifier: Programming Language :: Python :: 3.9
Provides-Extra: postgres
Requires-Dist: Jinja2 (>=2.11.3,<2.12.0)
Requires-Dist: SQLAlchemy (>=1.3.6,<2.0.0); extra == "postgres"
Requires-Dist: amundsen-databuilder (>=6.0.0,<7.0.0)
Requires-Dist: boto3 (>=1.24.24,<1.25.0)
Requires-Dist: click-spinner (>=0.1.10,<0.2.0)
Requires-Dist: pandas (>=1.3.5,<2.0.0)
Requires-Dist: psycopg2 (>=2.8.6,<2.9.0); extra == "postgres"
Requires-Dist: ruamel.yaml (>=0.16.12,<0.17.0)
Requires-Dist: typer (>=0.4.1,<0.5.0)
Project-URL: Documentation, https://docs.cartedata.com
Project-URL: Repository, https://github.com/carte-data/carte
